twitter.common.confluence-0.3.10-py2.7-nspkg.pth
twitter/common/confluence/__init__.py
twitter/common/confluence/confluence.py
twitter.common.confluence-0.3.10.dist-info/DESCRIPTION.rst
twitter.common.confluence-0.3.10.dist-info/METADATA
twitter.common.confluence-0.3.10.dist-info/RECORD
twitter.common.confluence-0.3.10.dist-info/WHEEL
twitter.common.confluence-0.3.10.dist-info/metadata.json
twitter.common.confluence-0.3.10.dist-info/namespace_packages.txt
twitter.common.confluence-0.3.10.dist-info/top_level.txt
twitter.common.confluence-0.3.10.dist-info/zip-safe
