Metadata-Version: 2.0
Name: twitter.common.confluence
Version: 0.3.10
Summary: Confluence utilities for twitter.
Home-page: https://github.com/twitter/commons
Author: UNKNOWN
Author-email: UNKNOWN
License: Apache License, Version 2.0
Platform: UNKNOWN
Classifier: Intended Audience :: Developers
Classifier: License :: OSI Approved :: Apache Software License
Classifier: Operating System :: OS Independent
Classifier: Programming Language :: Python
Requires-Dist: twitter.common.log (==0.3.10)
